simple_counter.v
module simple_counter(clk,rst,count);
input clk,rst;
output [31:0]count;
reg [31:0]count;

always @(posedge clk or posedge rst)
begin
	if (rst)
		count<=32'b0;
	else 
		count<=count+1;
end
endmodule

counter_tb.v
module counter_tb;

  reg clk, rst;
  wire [31:0]count;

  // Instantiate the simple_counter module
  simple_counter sc (
    .clk(clk),
    .rst(rst),
    .count(count)
  );

  // Generate the clock signal with a period of 10 time units
  initial clk = 1'b0;
  always #5 clk = ~clk;

  // Apply reset and release it after some time
  initial begin
    $dumpfile("counter_result.vcd");
    $dumpvars(0, counter_tb);
    
    // Apply reset
    rst = 1'b1;
    #10;
    rst = 1'b0;

    // Finish simulation after 500 time units
    #500;
    $finish;
  end

endmodule

counter_result.vcd
$date
	Thu Sep 12 17:48:44 2024
$end
$version
	Icarus Verilog
$end
$timescale
	1s
$end
$scope module counter_tb $end
$var wire 32 ! count [31:0] $end
$var reg 1 " clk $end
$var reg 1 # rst $end
$scope module sc $end
$var wire 1 " clk $end
$var wire 1 # rst $end
$var reg 32 $ count [31:0] $end
$upscope $end
$upscope $end
$enddefinitions $end
$comment Show the parameter values. $end
$dumpall
$end
#0
$dumpvars
b0 $
1#
0"
b0 !
$end
#5
1"
#10
0"
0#
#15
b1 !
b1 $
1"
#20
0"
#25
b10 !
b10 $
1"
#30
0"
#35
b11 !
b11 $
1"
#40
0"
#45
b100 !
b100 $
1"
#50
0"
#55
b101 !
b101 $
1"
#60
0"
#65
b110 !
b110 $
1"
#70
0"
#75
b111 !
b111 $
1"
#80
0"
#85
b1000 !
b1000 $
1"
#90
0"
#95
b1001 !
b1001 $
1"
#100
0"
#105
b1010 !
b1010 $
1"
#110
0"
#115
b1011 !
b1011 $
1"
#120
0"
#125
b1100 !
b1100 $
1"
#130
0"
#135
b1101 !
b1101 $
1"
#140
0"
#145
b1110 !
b1110 $
1"
#150
0"
#155
b1111 !
b1111 $
1"
#160
0"
#165
b10000 !
b10000 $
1"
#170
0"
#175
b10001 !
b10001 $
1"
#180
0"
#185
b10010 !
b10010 $
1"
#190
0"
#195
b10011 !
b10011 $
1"
#200
0"
#205
b10100 !
b10100 $
1"
#210
0"
#215
b10101 !
b10101 $
1"
#220
0"
#225
b10110 !
b10110 $
1"
#230
0"
#235
b10111 !
b10111 $
1"
#240
0"
#245
b11000 !
b11000 $
1"
#250
0"
#255
b11001 !
b11001 $
1"
#260
0"
#265
b11010 !
b11010 $
1"
#270
0"
#275
b11011 !
b11011 $
1"
#280
0"
#285
b11100 !
b11100 $
1"
#290
0"
#295
b11101 !
b11101 $
1"
#300
0"
#305
b11110 !
b11110 $
1"
#310
0"
#315
b11111 !
b11111 $
1"
#320
0"
#325
b100000 !
b100000 $
1"
#330
0"
#335
b100001 !
b100001 $
1"
#340
0"
#345
b100010 !
b100010 $
1"
#350
0"
#355
b100011 !
b100011 $
1"
#360
0"
#365
b100100 !
b100100 $
1"
#370
0"
#375
b100101 !
b100101 $
1"
#380
0"
#385
b100110 !
b100110 $
1"
#390
0"
#395
b100111 !
b100111 $
1"
#400
0"
#405
b101000 !
b101000 $
1"
#410
0"
#415
b101001 !
b101001 $
1"
#420
0"
#425
b101010 !
b101010 $
1"
#430
0"
#435
b101011 !
b101011 $
1"
#440
0"
#445
b101100 !
b101100 $
1"
#450
0"
#455
b101101 !
b101101 $
1"
#460
0"
#465
b101110 !
b101110 $
1"
#470
0"
#475
b101111 !
b101111 $
1"
#480
0"
#485
b110000 !
b110000 $
1"
#490
0"
#495
b110001 !
b110001 $
1"
#500
0"
#505
b110010 !
b110010 $
1"
