parallel_adder_8bit.v
//8 bit parallel adder 8 bit using operater assignments 
module parallel_adder_8bit(sum,cout,in1,in2,cin);
input [7:0]in1,in2;
input cin;
output [7:0]sum;
output cout;

assign #10 {cout,sum} = in1+in2+cin;
endmodule

parallel_adder_8bit_tb.v
module parallel_adder_8bit_tb;

/*input [7:0]in1,in2;
input cin;
output [7:0]sum;
output cout;
*/

reg [7:0]in1,in2;
reg cin;
wire [7:0]sum;
wire cout;

parallel_adder_8bit PA(.sum(sum),
		      .cout(cout),
		      .in1(in1),
		      .in2(in2),
		      .cin(cin));
		   
initial 
begin
	$dumpfile("parallel_adder_8bit_result.vcd"); $dumpvars(0,parallel_adder_8bit_tb);
	 in1=10; in2=5; cin=0;
	#11 in1=11; in2=6; cin=1;
	#11 in1=12; in2=7; cin=0;
	#11 in1=13; in2=8; cin=1;
	#11 in1=14; in2=9; cin=0;
	#11 in1=15; in2=10; cin=1;
end
initial # 1000 $finish;
endmodule

parallel_adder_8bit_result.vcd
$date
	Thu Sep 12 18:05:51 2024
$end
$version
	Icarus Verilog
$end
$timescale
	1s
$end
$scope module parallel_adder_8bit_tb $end
$var wire 8 ! sum [7:0] $end
$var wire 1 " cout $end
$var reg 1 # cin $end
$var reg 8 $ in1 [7:0] $end
$var reg 8 % in2 [7:0] $end
$scope module PA $end
$var wire 1 # cin $end
$var wire 8 & in1 [7:0] $end
$var wire 8 ' in2 [7:0] $end
$var wire 8 ( sum [7:0] $end
$var wire 1 " cout $end
$upscope $end
$upscope $end
$enddefinitions $end
$comment Show the parameter values. $end
$dumpall
$end
#0
$dumpvars
bx (
b101 '
b1010 &
b101 %
b1010 $
0#
x"
bx !
$end
#10
b1111 !
b1111 (
0"
#11
1#
b110 %
b110 '
b1011 $
b1011 &
#21
b10010 !
b10010 (
#22
0#
b111 %
b111 '
b1100 $
b1100 &
#32
b10011 !
b10011 (
#33
1#
b1000 %
b1000 '
b1101 $
b1101 &
#43
b10110 !
b10110 (
#44
0#
b1001 %
b1001 '
b1110 $
b1110 &
#54
b10111 !
b10111 (
#55
1#
b1010 %
b1010 '
b1111 $
b1111 &
#65
b11010 !
b11010 (
