FIFO/fifo.v
module fifo(dout, din, full, empty, rst, wr, rd, clk);
    input rst, wr, rd, clk;
    input [7:0] din;
    output reg [7:0] dout;
    output full, empty;

    reg [7:0] mem[255:0];  // Memory array
    reg [7:0] wptr, rptr;  // Write and read pointers

    // Write logic
    always @(posedge clk) begin
        if (rst) begin
            wptr <= 0;
        end else if (wr && !full) begin  // Write only if not full
            mem[wptr] <= din;
            wptr <= wptr + 1; 
            if (wptr == 8'b1111_1111) wptr <= 0;  // Wrap-around logic for wptr
        end
    end

    // Read logic
    always @(posedge clk) begin
        if (rst) begin
            rptr <= 0;
        end else if (rd && !empty) begin  // Read only if not empty
            dout <= mem[rptr];
            rptr <= rptr + 1;
            if (rptr == 8'b1111_1111) rptr <= 0;  // Wrap-around logic for rptr
        end
    end

    // Full condition: FIFO is full when write pointer is just behind the read pointer
    assign full = ((wptr + 1 == rptr) || (wptr == 8'b1111_1111 && rptr == 8'b0000_0000)) ? 1 : 0;

    // Empty condition: FIFO is empty when read and write pointers are the same
    assign empty = (wptr == rptr) ? 1 : 0;

endmodule

FIFO/fifo_tb.v
module fifo_tb;

    // Testbench signals
    reg rst, wr, rd, clk;        // Control signals
    reg [7:0] din;               // Data input
    wire [7:0] dout;             // Data output from FIFO
    wire full, empty;            // Status signals from FIFO

    // Instantiate the FIFO module
    fifo uut (
        .dout(dout), 
        .din(din), 
        .full(full), 
        .empty(empty), 
        .rst(rst), 
        .wr(wr), 
        .rd(rd), 
        .clk(clk)
    );

    // Clock generation: 10ns clock period
    initial begin
        clk = 0;
        forever #5 clk = ~clk;
    end

    // Test sequence
    initial begin
        $dumpfile("fifo_test.vcd"); // Output the waveform file
        $dumpvars(0, fifo_tb);

        // Initialize signals
        #5 rst = 1;  // Assert reset
        wr = 0;
        rd = 0;
        din = 0;

        // Deassert reset
        #20 rst = 0;

        // Write to FIFO
        #10 wr = 1; din = 8'hAA;  // Write first data (0xAA)
        #10 din = 8'hBB;          // Write second data (0xBB)
        #10 din = 8'hCC;          // Write third data (0xCC)
        #10 din = 8'hDD;          // Write fourth data (0xDD)
        #10 wr = 0;               // Stop writing

        // Start reading from FIFO
        #20 rd = 1;
        #10 rd = 0;

        // Read remaining data
        #20 rd = 1;
        #30 rd = 0;

        // Finish simulation
        #100 $finish;
    end

endmodule

FIFO/fifo_test.vcd
$date
	Wed Sep 25 23:09:27 2024
$end
$version
	Icarus Verilog
$end
$timescale
	1s
$end
$scope module fifo_tb $end
$var wire 1 ! full $end
$var wire 1 " empty $end
$var wire 8 # dout [7:0] $end
$var reg 1 $ clk $end
$var reg 8 % din [7:0] $end
$var reg 1 & rd $end
$var reg 1 ' rst $end
$var reg 1 ( wr $end
$scope module uut $end
$var wire 1 $ clk $end
$var wire 8 ) din [7:0] $end
$var wire 1 & rd $end
$var wire 1 ' rst $end
$var wire 1 ( wr $end
$var wire 1 ! full $end
$var wire 1 " empty $end
$var reg 8 * dout [7:0] $end
$var reg 8 + rptr [7:0] $end
$var reg 8 , wptr [7:0] $end
$upscope $end
$upscope $end
$enddefinitions $end
$comment Show the parameter values. $end
$dumpall
$end
#0
$dumpvars
bx ,
bx +
bx *
bx )
x(
x'
x&
bx %
0$
bx #
x"
x!
$end
#5
0!
1"
b0 ,
b0 +
b0 %
b0 )
0&
0(
1'
1$
#10
0$
#15
1$
#20
0$
#25
1$
0'
#30
0$
#35
0"
b1 ,
1$
b10101010 %
b10101010 )
1(
#40
0$
#45
b10 ,
1$
b10111011 %
b10111011 )
#50
0$
#55
b11 ,
1$
b11001100 %
b11001100 )
#60
0$
#65
b100 ,
1$
b11011101 %
b11011101 )
#70
0$
#75
1$
0(
#80
0$
#85
1$
#90
0$
#95
b1 +
b10101010 #
b10101010 *
1$
1&
#100
0$
#105
1$
0&
#110
0$
#115
1$
#120
0$
#125
b10 +
b10111011 #
b10111011 *
1$
1&
#130
0$
#135
b11 +
b11001100 #
b11001100 *
1$
#140
0$
#145
1"
b100 +
b11011101 #
b11011101 *
1$
#150
0$
#155
1$
0&
