REG32x32/file.v
module file(rd_data1,rd_data2,src_add1,src_add2,wr_data_in,wr_data_add,write,clk);

output [31:0]rd_data1,rd_data2;
input [4:0]src_add1,src_add2;
input write,clk;
input [32:0]wr_data_in;
input [4:0]wr_data_add;
reg [31:0]mem[31:0];

assign rd_data1 = mem[src_add1];
assign rd_data2 = mem[src_add2];

always @(posedge clk)
begin
	if(write) mem[wr_data_add]=wr_data_in;
end
endmodule

REG32x32/filetb.v
module filetb;


wire [31:0]rd_data1,rd_data2;
reg [4:0]src_add1,src_add2;
reg write,clk;
reg [32:0]wr_data_in;
reg [4:0]wr_data_add;

file ff(rd_data1,rd_data2,src_add1,src_add2,wr_data_in,wr_data_add,write,clk);
integer i=0;

initial clk=1'b0;

always #5 clk=~clk;
initial 
begin
$dumpfile("res.vcd"); $dumpvars;
	#2 write =1;
	for (i=0;i<32;i=i+1)
	begin
		wr_data_add=i;
		wr_data_in=$random;
		#10;
	end
		#2 write =0;
	for (i=0;i<32;i=i+1)
	begin
		src_add1=i;
		#10;
	end
	for (i=0;i<32;i=i+1)
	begin
		src_add2=i;
		#10;
	end
	#1000 $finish;
end
endmodule

REG32x32/res.vcd
$date
	Thu Sep 26 13:21:49 2024
$end
$version
	Icarus Verilog
$end
$timescale
	1s
$end
$scope module filetb $end
$var wire 32 ! rd_data2 [31:0] $end
$var wire 32 " rd_data1 [31:0] $end
$var reg 1 # clk $end
$var reg 5 $ src_add1 [4:0] $end
$var reg 5 % src_add2 [4:0] $end
$var reg 5 & wr_data_add [4:0] $end
$var reg 33 ' wr_data_in [32:0] $end
$var reg 1 ( write $end
$var integer 32 ) i [31:0] $end
$scope module ff $end
$var wire 1 # clk $end
$var wire 32 * rd_data1 [31:0] $end
$var wire 32 + rd_data2 [31:0] $end
$var wire 5 , src_add1 [4:0] $end
$var wire 5 - src_add2 [4:0] $end
$var wire 5 . wr_data_add [4:0] $end
$var wire 33 / wr_data_in [32:0] $end
$var wire 1 ( write $end
$upscope $end
$upscope $end
$enddefinitions $end
$comment Show the parameter values. $end
$dumpall
$end
#0
$dumpvars
bx /
bx .
bx -
bx ,
bx +
bx *
b0 )
x(
bx '
bx &
bx %
bx $
0#
bx "
bx !
$end
#2
b10010000101010011010100100100 '
b10010000101010011010100100100 /
b0 &
b0 .
1(
#5
1#
#10
0#
#12
b111000000100010010101111010000001 '
b111000000100010010101111010000001 /
b1 &
b1 .
b1 )
#15
1#
#20
0#
#22
b110000100100001001101011000001001 '
b110000100100001001101011000001001 /
b10 &
b10 .
b10 )
#25
1#
#30
0#
#32
b110110001111100000101011001100011 '
b110110001111100000101011001100011 /
b11 &
b11 .
b11 )
#35
1#
#40
0#
#42
b110101110010111101100001101 '
b110101110010111101100001101 /
b100 &
b100 .
b100 )
#45
1#
#50
0#
#52
b1000110110111111001100110001101 '
b1000110110111111001100110001101 /
b101 &
b101 .
b101 )
#55
1#
#60
0#
#62
b110110010110000101000010001100101 '
b110110010110000101000010001100101 /
b110 &
b110 .
b110 )
#65
1#
#70
0#
#72
b110001001001101110101001000010010 '
b110001001001101110101001000010010 /
b111 &
b111 .
b111 )
#75
1#
#80
0#
#82
b111100111110001100000001 '
b111100111110001100000001 /
b1000 &
b1000 .
b1000 )
#85
1#
#90
0#
#92
b110110101111100110100001101 '
b110110101111100110100001101 /
b1001 &
b1001 .
b1001 )
#95
1#
#100
0#
#102
b111011001000111111000101110110 '
b111011001000111111000101110110 /
b1010 &
b1010 .
b1010 )
#105
1#
#110
0#
#112
b11110100011011100110100111101 '
b11110100011011100110100111101 /
b1011 &
b1011 .
b1011 )
#115
1#
#120
0#
#122
b1110110110101000101011111101101 '
b1110110110101000101011111101101 /
b1100 &
b1100 .
b1100 )
#125
1#
#130
0#
#132
b1000110001011011111011110001100 '
b1000110001011011111011110001100 /
b1101 &
b1101 .
b1101 )
#135
1#
#140
0#
#142
b1111100111111011110100111111001 '
b1111100111111011110100111111001 /
b1110 &
b1110 .
b1110 )
#145
1#
#150
0#
#152
b111100011001101110010010011000110 '
b111100011001101110010010011000110 /
b1111 &
b1111 .
b1111 )
#155
1#
#160
0#
#162
b111100010111101111000010011000101 '
b111100010111101111000010011000101 /
b10000 &
b10000 .
b10000 )
#165
1#
#170
0#
#172
b111010101000100111101001010101010 '
b111010101000100111101001010101010 /
b10001 &
b10001 .
b10001 )
#175
1#
#180
0#
#182
b1110010101011111111011111100101 '
b1110010101011111111011111100101 /
b10010 &
b10010 .
b10010 )
#185
1#
#190
0#
#192
b110111011110100100111001001110111 '
b110111011110100100111001001110111 /
b10011 &
b10011 .
b10011 )
#195
1#
#200
0#
#202
b110001001001100101101011000010010 '
b110001001001100101101011000010010 /
b10100 &
b10100 .
b10100 )
#205
1#
#210
0#
#212
b1000111111011001101101110001111 '
b1000111111011001101101110001111 /
b10101 &
b10101 .
b10101 )
#215
1#
#220
0#
#222
b1111001001100000110100111110010 '
b1111001001100000110100111110010 /
b10110 &
b10110 .
b10110 )
#225
1#
#230
0#
#232
b111100111011101101001011011001110 '
b111100111011101101001011011001110 /
b10111 &
b10111 .
b10111 )
#235
1#
#240
0#
#242
b111110100000000000111101011101000 '
b111110100000000000111101011101000 /
b11000 &
b11000 .
b11000 )
#245
1#
#250
0#
#252
b111100010110010100100111011000101 '
b111100010110010100100111011000101 /
b11001 &
b11001 .
b11001 )
#255
1#
#260
0#
#262
b101110010110000100100101011100 '
b101110010110000100100101011100 /
b11010 &
b11010 .
b11010 )
#265
1#
#270
0#
#272
b111011110100011100010100010111101 '
b111011110100011100010100010111101 /
b11011 &
b11011 .
b11011 )
#275
1#
#280
0#
#282
b110010110101010110101100000101101 '
b110010110101010110101100000101101 /
b11100 &
b11100 .
b11100 )
#285
1#
#290
0#
#292
b110110010101001110010011001100101 '
b110110010101001110010011001100101 /
b11101 &
b11101 .
b11101 )
#295
1#
#300
0#
#302
b110110001111011110110001001100011 '
b110110001111011110110001001100011 /
b11110 &
b11110 .
b11110 )
#305
1#
#310
0#
#312
b101011100111000011100001010 '
b101011100111000011100001010 /
b11111 &
b11111 .
b11111 )
#315
1#
#320
0#
#322
b100000 )
#324
b10010000101010011010100100100 "
b10010000101010011010100100100 *
b0 $
b0 ,
b0 )
0(
#325
1#
#330
0#
#334
b11000000100010010101111010000001 "
b11000000100010010101111010000001 *
b1 $
b1 ,
b1 )
#335
1#
#340
0#
#344
b10000100100001001101011000001001 "
b10000100100001001101011000001001 *
b10 $
b10 ,
b10 )
#345
1#
#350
0#
#354
b10110001111100000101011001100011 "
b10110001111100000101011001100011 *
b11 $
b11 ,
b11 )
#355
1#
#360
0#
#364
b110101110010111101100001101 "
b110101110010111101100001101 *
b100 $
b100 ,
b100 )
#365
1#
#370
0#
#374
b1000110110111111001100110001101 "
b1000110110111111001100110001101 *
b101 $
b101 ,
b101 )
#375
1#
#380
0#
#384
b10110010110000101000010001100101 "
b10110010110000101000010001100101 *
b110 $
b110 ,
b110 )
#385
1#
#390
0#
#394
b10001001001101110101001000010010 "
b10001001001101110101001000010010 *
b111 $
b111 ,
b111 )
#395
1#
#400
0#
#404
b111100111110001100000001 "
b111100111110001100000001 *
b1000 $
b1000 ,
b1000 )
#405
1#
#410
0#
#414
b110110101111100110100001101 "
b110110101111100110100001101 *
b1001 $
b1001 ,
b1001 )
#415
1#
#420
0#
#424
b111011001000111111000101110110 "
b111011001000111111000101110110 *
b1010 $
b1010 ,
b1010 )
#425
1#
#430
0#
#434
b11110100011011100110100111101 "
b11110100011011100110100111101 *
b1011 $
b1011 ,
b1011 )
#435
1#
#440
0#
#444
b1110110110101000101011111101101 "
b1110110110101000101011111101101 *
b1100 $
b1100 ,
b1100 )
#445
1#
#450
0#
#454
b1000110001011011111011110001100 "
b1000110001011011111011110001100 *
b1101 $
b1101 ,
b1101 )
#455
1#
#460
0#
#464
b1111100111111011110100111111001 "
b1111100111111011110100111111001 *
b1110 $
b1110 ,
b1110 )
#465
1#
#470
0#
#474
b11100011001101110010010011000110 "
b11100011001101110010010011000110 *
b1111 $
b1111 ,
b1111 )
#475
1#
#480
0#
#484
b11100010111101111000010011000101 "
b11100010111101111000010011000101 *
b10000 $
b10000 ,
b10000 )
#485
1#
#490
0#
#494
b11010101000100111101001010101010 "
b11010101000100111101001010101010 *
b10001 $
b10001 ,
b10001 )
#495
1#
#500
0#
#504
b1110010101011111111011111100101 "
b1110010101011111111011111100101 *
b10010 $
b10010 ,
b10010 )
#505
1#
#510
0#
#514
b10111011110100100111001001110111 "
b10111011110100100111001001110111 *
b10011 $
b10011 ,
b10011 )
#515
1#
#520
0#
#524
b10001001001100101101011000010010 "
b10001001001100101101011000010010 *
b10100 $
b10100 ,
b10100 )
#525
1#
#530
0#
#534
b1000111111011001101101110001111 "
b1000111111011001101101110001111 *
b10101 $
b10101 ,
b10101 )
#535
1#
#540
0#
#544
b1111001001100000110100111110010 "
b1111001001100000110100111110010 *
b10110 $
b10110 ,
b10110 )
#545
1#
#550
0#
#554
b11100111011101101001011011001110 "
b11100111011101101001011011001110 *
b10111 $
b10111 ,
b10111 )
#555
1#
#560
0#
#564
b11110100000000000111101011101000 "
b11110100000000000111101011101000 *
b11000 $
b11000 ,
b11000 )
#565
1#
#570
0#
#574
b11100010110010100100111011000101 "
b11100010110010100100111011000101 *
b11001 $
b11001 ,
b11001 )
#575
1#
#580
0#
#584
b101110010110000100100101011100 "
b101110010110000100100101011100 *
b11010 $
b11010 ,
b11010 )
#585
1#
#590
0#
#594
b11011110100011100010100010111101 "
b11011110100011100010100010111101 *
b11011 $
b11011 ,
b11011 )
#595
1#
#600
0#
#604
b10010110101010110101100000101101 "
b10010110101010110101100000101101 *
b11100 $
b11100 ,
b11100 )
#605
1#
#610
0#
#614
b10110010101001110010011001100101 "
b10110010101001110010011001100101 *
b11101 $
b11101 ,
b11101 )
#615
1#
#620
0#
#624
b10110001111011110110001001100011 "
b10110001111011110110001001100011 *
b11110 $
b11110 ,
b11110 )
#625
1#
#630
0#
#634
b101011100111000011100001010 "
b101011100111000011100001010 *
b11111 $
b11111 ,
b11111 )
#635
1#
#640
0#
#644
b10010000101010011010100100100 !
b10010000101010011010100100100 +
b0 %
b0 -
b0 )
#645
1#
#650
0#
#654
b11000000100010010101111010000001 !
b11000000100010010101111010000001 +
b1 %
b1 -
b1 )
#655
1#
#660
0#
#664
b10000100100001001101011000001001 !
b10000100100001001101011000001001 +
b10 %
b10 -
b10 )
#665
1#
#670
0#
#674
b10110001111100000101011001100011 !
b10110001111100000101011001100011 +
b11 %
b11 -
b11 )
#675
1#
#680
0#
#684
b110101110010111101100001101 !
b110101110010111101100001101 +
b100 %
b100 -
b100 )
#685
1#
#690
0#
#694
b1000110110111111001100110001101 !
b1000110110111111001100110001101 +
b101 %
b101 -
b101 )
#695
1#
#700
0#
#704
b10110010110000101000010001100101 !
b10110010110000101000010001100101 +
b110 %
b110 -
b110 )
#705
1#
#710
0#
#714
b10001001001101110101001000010010 !
b10001001001101110101001000010010 +
b111 %
b111 -
b111 )
#715
1#
#720
0#
#724
b111100111110001100000001 !
b111100111110001100000001 +
b1000 %
b1000 -
b1000 )
#725
1#
#730
0#
#734
b110110101111100110100001101 !
b110110101111100110100001101 +
b1001 %
b1001 -
b1001 )
#735
1#
#740
0#
#744
b111011001000111111000101110110 !
b111011001000111111000101110110 +
b1010 %
b1010 -
b1010 )
#745
1#
#750
0#
#754
b11110100011011100110100111101 !
b11110100011011100110100111101 +
b1011 %
b1011 -
b1011 )
#755
1#
#760
0#
#764
b1110110110101000101011111101101 !
b1110110110101000101011111101101 +
b1100 %
b1100 -
b1100 )
#765
1#
#770
0#
#774
b1000110001011011111011110001100 !
b1000110001011011111011110001100 +
b1101 %
b1101 -
b1101 )
#775
1#
#780
0#
#784
b1111100111111011110100111111001 !
b1111100111111011110100111111001 +
b1110 %
b1110 -
b1110 )
#785
1#
#790
0#
#794
b11100011001101110010010011000110 !
b11100011001101110010010011000110 +
b1111 %
b1111 -
b1111 )
#795
1#
#800
0#
#804
b11100010111101111000010011000101 !
b11100010111101111000010011000101 +
b10000 %
b10000 -
b10000 )
#805
1#
#810
0#
#814
b11010101000100111101001010101010 !
b11010101000100111101001010101010 +
b10001 %
b10001 -
b10001 )
#815
1#
#820
0#
#824
b1110010101011111111011111100101 !
b1110010101011111111011111100101 +
b10010 %
b10010 -
b10010 )
#825
1#
#830
0#
#834
b10111011110100100111001001110111 !
b10111011110100100111001001110111 +
b10011 %
b10011 -
b10011 )
#835
1#
#840
0#
#844
b10001001001100101101011000010010 !
b10001001001100101101011000010010 +
b10100 %
b10100 -
b10100 )
#845
1#
#850
0#
#854
b1000111111011001101101110001111 !
b1000111111011001101101110001111 +
b10101 %
b10101 -
b10101 )
#855
1#
#860
0#
#864
b1111001001100000110100111110010 !
b1111001001100000110100111110010 +
b10110 %
b10110 -
b10110 )
#865
1#
#870
0#
#874
b11100111011101101001011011001110 !
b11100111011101101001011011001110 +
b10111 %
b10111 -
b10111 )
#875
1#
#880
0#
#884
b11110100000000000111101011101000 !
b11110100000000000111101011101000 +
b11000 %
b11000 -
b11000 )
#885
1#
#890
0#
#894
b11100010110010100100111011000101 !
b11100010110010100100111011000101 +
b11001 %
b11001 -
b11001 )
#895
1#
#900
0#
#904
b101110010110000100100101011100 !
b101110010110000100100101011100 +
b11010 %
b11010 -
b11010 )
#905
1#
#910
0#
#914
b11011110100011100010100010111101 !
b11011110100011100010100010111101 +
b11011 %
b11011 -
b11011 )
#915
1#
#920
0#
#924
b10010110101010110101100000101101 !
b10010110101010110101100000101101 +
b11100 %
b11100 -
b11100 )
#925
1#
#930
0#
#934
b10110010101001110010011001100101 !
b10110010101001110010011001100101 +
b11101 %
b11101 -
b11101 )
#935
1#
#940
0#
#944
b10110001111011110110001001100011 !
b10110001111011110110001001100011 +
b11110 %
b11110 -
b11110 )
#945
1#
#950
0#
#954
b101011100111000011100001010 !
b101011100111000011100001010 +
b11111 %
b11111 -
b11111 )
#955
1#
#960
0#
#964
b100000 )
