gcd/controller.v
module controller(
    input clk,
    input lt,
    input gt,
    input eq,
    input start,
    output reg ldA,
    output reg ldB,
    output reg sel1,
    output reg sel2,
    output reg sel_in,
    output reg done
    );
     
    reg [2:0] state;
parameter     S0 = 3'b000 , S1 = 3'b001 , S2 = 3'b010 , S3 = 3'b011 , S4 = 3'b100 , S5 = 3'b101;

/************** State Transitions *******************/

always @(posedge clk)    
        begin 
            case(state)
                S0: if(start) state <= S1;
                S1: state<= S2;
                S2: #2 if(eq) state<= S5;
                         else if(lt) state<= S3;
                         else if(gt) state<= S4;
                S3: #2 if(eq) state<= S5;
                         else if(lt) state<= S3;
                         else if(gt) state<= S4;
                S4: #2 if(eq) state<= S5;
                         else if(lt) state<= S3;
                         else if(gt) state<= S4;
                S5: state<= S5;
                default: state<= S0;
            endcase
        end 
            
/********** Generation of Load Signals ****************/     
     
always@(*)     
     begin
        case(state)
                S0: begin sel_in = 1; ldA = 1; ldB = 0; done = 0; end
                S1: begin sel_in = 1; ldA = 0; ldB = 1; end
                S2: if(eq) done = 1; 
                     else if(lt) begin 
                            sel1 = 1; sel2 = 0; sel_in = 0;
                            #1 ldA = 0; ldB = 1;
                            end
                     else if(gt) begin
                            sel1 = 0; sel2 = 1; sel_in = 0;
                            #1 ldA = 1; ldB = 0; 
                            end
                S3: if(eq) done = 1; 
                     else if(lt) begin 
                            sel1 = 1; sel2 = 0; sel_in = 0;
                            #1 ldA = 0; ldB = 1;
                            end
                     else if(gt) begin
                            sel1 = 0; sel2 = 1; sel_in = 0;
                            #1 ldA = 1; ldB = 0; 
                            end
                S4: if(eq) done = 1; 
                     else if(lt) begin 
                            sel1 = 1; sel2 = 0; sel_in = 0;
                            #1 ldA = 0; ldB = 1;
                            end
                     else if(gt) begin
                            sel1 = 0; sel2 = 1; sel_in = 0;
                            #1 ldA = 1; ldB = 0; 
                            end
                S5: begin 
                        done = 1 ; sel1 = 0; sel2 = 0 ; sel_in = 0 ; ldA = 0 ; ldB = 0;
                     end
                default : begin ldA = 0; ldB = 0 ; end
                
            endcase
        end

        
endmodule

gcd/COMPARE.v
module COMPARE(lt, gt, eq, data1,data2);
  input [15:0] data1,data2;
  output lt, gt, eq;

  assign lt = data1< data2;  // Correct: lt should be assigned for v1 < v2
  assign gt = data1>data2;  // Correct: gt should be assigned for v1 > v2
  assign eq = data1 == data2; // Correct: eq should be assigned for v1 == v2

endmodule

gcd/SUB.v
module SUB(out,in1,in2);
input [15:0]in1,in2;

output reg [15:0]out;

always @ (*) out = in1-in2;

endmodule

gcd/MUX.v
module MUX(out,in0,in1,sel);
input [15:0]in0,in1;
input sel;
output [15:0]out;

assign out=sel?in1:in0;

endmodule

gcd/PIPO.v
module PIPO(data_out,data_in,load,clk);
input load,clk;
input [15:0]data_in;
output reg [15:0]data_out;

always @(posedge clk)
if(load) data_out<=data_in;
endmodule

gcd/gcd_top.v
module gcd_top(
    input ldA,
    input ldB,
    input sel1,
    input sel2,
    input sel_in,
    input clk,
    input [15:0] data_in,
    output gt,
    output lt,
    output eq
    );

wire [15:0] Aout,Bout,X,Y,Bus,SubOut;

PIPO A (Aout,Bus,ldA,clk);
PIPO B (Bout,Bus,ldB,clk);
MUX MUX_in1 (X,Aout,Bout,sel1);
MUX MUX_in2 (Y,Aout,Bout,sel2);
MUX MUX_load (Bus,SubOut,data_in,sel_in);
SUB SB (SubOut,X,Y);
COMPARE COMP (lt,gt,eq,Aout,Bout);

endmodule

gcd/test.v
module test;

reg [15:0] data_in;
reg clk, start;
wire done;


  gcd_top DP (ldA,ldB,sel1,sel2,sel_in,clk,data_in,gt,lt,eq);
  controller CON (clk,lt,gt,eq,start,ldA,ldB,sel1,sel2,sel_in,done);

initial 
    begin
        clk = 1'b0;
        #3 start = 1'b1;
        #1000 $finish;
    end
    
always #5 clk = ~clk; // Clock period = 10 //
    
initial 
    begin
        #4 data_in = 143;
        #10 data_in    = 78;
    end

initial 
        begin
            $monitor($time, "GCD = %d Status = %b",DP.Aout,done);
            $dumpfile ("gcd.vcd");
            $dumpvars(0,test);
        end    
        
endmodule

gcd/gcd.vcd
$date
	Sat Sep 21 13:21:21 2024
$end
$version
	Icarus Verilog
$end
$timescale
	1s
$end
$scope module test $end
$var wire 1 ! sel_in $end
$var wire 1 " sel2 $end
$var wire 1 # sel1 $end
$var wire 1 $ lt $end
$var wire 1 % ldB $end
$var wire 1 & ldA $end
$var wire 1 ' gt $end
$var wire 1 ( eq $end
$var wire 1 ) done $end
$var reg 1 * clk $end
$var reg 16 + data_in [15:0] $end
$var reg 1 , start $end
$scope module CON $end
$var wire 1 * clk $end
$var wire 1 , start $end
$var wire 1 $ lt $end
$var wire 1 ' gt $end
$var wire 1 ( eq $end
$var parameter 3 - S0 $end
$var parameter 3 . S1 $end
$var parameter 3 / S2 $end
$var parameter 3 0 S3 $end
$var parameter 3 1 S4 $end
$var parameter 3 2 S5 $end
$var reg 1 ) done $end
$var reg 1 & ldA $end
$var reg 1 % ldB $end
$var reg 1 # sel1 $end
$var reg 1 " sel2 $end
$var reg 1 ! sel_in $end
$var reg 3 3 state [2:0] $end
$upscope $end
$scope module DP $end
$var wire 1 * clk $end
$var wire 16 4 data_in [15:0] $end
$var wire 1 & ldA $end
$var wire 1 % ldB $end
$var wire 1 # sel1 $end
$var wire 1 " sel2 $end
$var wire 1 ! sel_in $end
$var wire 1 $ lt $end
$var wire 1 ' gt $end
$var wire 1 ( eq $end
$var wire 16 5 Y [15:0] $end
$var wire 16 6 X [15:0] $end
$var wire 16 7 SubOut [15:0] $end
$var wire 16 8 Bus [15:0] $end
$var wire 16 9 Bout [15:0] $end
$var wire 16 : Aout [15:0] $end
$scope module A $end
$var wire 1 * clk $end
$var wire 1 & load $end
$var wire 16 ; data_in [15:0] $end
$var reg 16 < data_out [15:0] $end
$upscope $end
$scope module B $end
$var wire 1 * clk $end
$var wire 1 % load $end
$var wire 16 = data_in [15:0] $end
$var reg 16 > data_out [15:0] $end
$upscope $end
$scope module COMP $end
$var wire 16 ? data1 [15:0] $end
$var wire 16 @ data2 [15:0] $end
$var wire 1 $ lt $end
$var wire 1 ' gt $end
$var wire 1 ( eq $end
$upscope $end
$scope module MUX_in1 $end
$var wire 16 A in0 [15:0] $end
$var wire 16 B in1 [15:0] $end
$var wire 1 # sel $end
$var wire 16 C out [15:0] $end
$upscope $end
$scope module MUX_in2 $end
$var wire 16 D in0 [15:0] $end
$var wire 16 E in1 [15:0] $end
$var wire 1 " sel $end
$var wire 16 F out [15:0] $end
$upscope $end
$scope module MUX_load $end
$var wire 16 G in1 [15:0] $end
$var wire 1 ! sel $end
$var wire 16 H out [15:0] $end
$var wire 16 I in0 [15:0] $end
$upscope $end
$scope module SB $end
$var wire 16 J in1 [15:0] $end
$var wire 16 K in2 [15:0] $end
$var reg 16 L out [15:0] $end
$upscope $end
$upscope $end
$upscope $end
$enddefinitions $end
$comment Show the parameter values. $end
$dumpall
b101 2
b100 1
b11 0
b10 /
b1 .
b0 -
$end
#0
$dumpvars
bx L
bx K
bx J
bx I
bx H
bx G
bx F
bx E
bx D
bx C
bx B
bx A
bx @
bx ?
bx >
bx =
bx <
bx ;
bx :
bx 9
bx 8
bx 7
bx 6
bx 5
bx 4
bx 3
x,
bx +
0*
x)
x(
x'
x&
x%
x$
x#
x"
x!
$end
#3
1,
#4
b10001111 +
b10001111 4
b10001111 G
#5
b10001111 8
b10001111 ;
b10001111 =
b10001111 H
0)
0%
1&
1!
b0 3
1*
#10
0*
#14
b1001110 8
b1001110 ;
b1001110 =
b1001110 H
b1001110 +
b1001110 4
b1001110 G
#15
1%
0&
b1 3
b1001110 :
b1001110 <
b1001110 ?
b1001110 A
b1001110 D
1*
#20
0*
#25
b0 7
b0 I
b0 L
b1001110 6
b1001110 C
b1001110 J
b1001110 5
b1001110 F
b1001110 K
1)
0$
0'
1(
b1001110 9
b1001110 >
b1001110 @
b1001110 B
b1001110 E
b10 3
1*
#30
0*
#35
1*
#37
b0 8
b0 ;
b0 =
b0 H
0%
0!
0"
0#
b101 3
