gcd/controller.v
module controller(ldA, ldB, sel1, sel2, sel_load, done, lt, gt, eq, clk, start);
    input clk, lt, gt, eq, start;
    output reg ldA, ldB, done, sel_load, sel1, sel2;

    reg [2:0] state;
    parameter s0 = 3'b000, s1 = 3'b001, s2 = 3'b010, s3 = 3'b011, s4 = 3'b100, s5 = 3'b101;

    // Sequential state transition logic
    always @(posedge clk)
    begin
        case (state)
            s0: if (start) state <= s1;
            s1: state <= s2;
            s2: if (lt) state <= s3;
                else if (gt) state <= s4;
                else if (eq) state <= s5;
            s3: if (lt) state <= s3;
                else if (gt) state <= s4;
                else if (eq) state <= s5;
            s4: if (lt) state <= s3;
                else if (gt) state <= s4;
                else if (eq) state <= s5;
            s5: state <= s5;
            default: state <= s0;
        endcase
    end

    // Combinational control signal logic
    always @(state)
    begin
        case (state)
            s0: begin  
                sel_load = 1;
                ldA = 1; 
                ldB = 0; 
                done = 0; 
            end

            s1: begin  
                sel_load = 1; 
		ldA = 0;
                ldB = 1; 
            end

            s2: if (lt) begin 
                    sel1 = 0; 
                    sel2=1;
                    sel_load = 0; 
                    ldA=0; ldB = 1; 
                end
                else if (gt) begin 
                    sel1 = 1; 
                    sel2 = 0; 
                    sel_load = 0;
                    ldB=0; ldA=1; 
                end
                else if (eq)  
                    done = 1; 
                      

            s3:if (lt) begin 
                    sel1 = 0; 
                    sel2=1;
                    sel_load = 0; 
                    ldA=0; ldB = 1; 
                end
                else if (gt) begin 
                    sel1 = 1; 
                    sel2 = 0; 
                    sel_load = 0;
                    ldB=0; ldA = 1; 
                end
                else if (eq)  
                    done = 1; 
                
            s4: if (lt) begin 
                    sel1 = 0; 
                    sel2=1;
                    sel_load = 0; 
                    ldA=0; ldB = 1; 
                end
                else if (gt) begin 
                    sel1 = 1; 
                    sel2 = 0; 
                    sel_load = 0;
                    ldB=0; ldA = 1; 
                end
                else if (eq)  
                    done = 1; 
       
                
            s5: begin 
                done=1;
                ldA=0;
                ldB=0; 
            end

            default: begin 
                ldA = 0; 
                ldB = 0; 
            end
        endcase
    end
endmodule

gcd/comparator.v
module comparator(lt,gt,eq,in0,in1);
input [15:0]in0,in1;
output lt,gt,eq;

assign lt=in0<in1;
assign gt=in0>in1;
assign eq=in0==in1;

endmodule

gcd/SUB.v
module SUB(out,data1,data2);
input [15:0]data1,data2;
output reg [15:0]out;

always @(*)
out<=data1-data2;

endmodule

gcd/MUX.v
module MUX(out,in0,in1,sel);
input [15:0]in0,in1;
input sel;
output [15:0]out;

assign out=sel?in1:in0;
endmodule

gcd/PIPO.v
module PIPO(output reg [15:0]dout,
	    input [15:0]din,
	    input clk,ld);
	    
always @(posedge clk)
if(ld) dout<=din;

endmodule

gcd/data_path.v
module data_path(lt,gt,eq,ldA,ldB,sel1,sel2,sel_load,clk,data_in);
input clk,sel1,sel2,sel_load,ldA,ldB;
input [15:0]data_in;
output lt,gt,eq;

wire [15:0]Aout,Bout,x,y,subout,Bus;

PIPO A(Aout,Bus,clk,ldA);
PIPO B(Bout,Bus,clk,ldB);
MUX MUX1(x,Bout,Aout,sel1);
MUX MUX2(y,Bout,Aout,sel2);
MUX MUX_load(Bus,subout,data_in,sel_load);
SUB SUBTRACTOR(subout,x,y);
comparator COMP(lt,gt,eq,Aout,Bout);
endmodule

gcd/test.v
module test;

reg [15:0]data_in;
reg clk,start;
wire done;

data_path DP(lt,gt,eq,ldA,ldB,sel1,sel2,sel_load,clk,data_in);
controller CON(ldA,ldB,sel1,sel2,sel_load,done,lt,gt,eq,clk,start);

initial
	begin
		clk=1'b0;
		#3 start = 1'b1;
		#1000 $finish;
	end
	
always #5 clk=~clk; 
initial
	begin
	#12 data_in = 143;
	#10 data_in = 78;
	end
	
initial
	begin
	$monitor($time, " %d-GCD %b-done",DP.Aout,done);
	$dumpfile("gcd.vcd");
	$dumpvars(0,test);
	end

endmodule

gcd/gcd.vcd
$date
	Sat Sep 21 22:18:54 2024
$end
$version
	Icarus Verilog
$end
$timescale
	1s
$end
$scope module test $end
$var wire 1 ! sel_load $end
$var wire 1 " sel2 $end
$var wire 1 # sel1 $end
$var wire 1 $ lt $end
$var wire 1 % ldB $end
$var wire 1 & ldA $end
$var wire 1 ' gt $end
$var wire 1 ( eq $end
$var wire 1 ) done $end
$var reg 1 * clk $end
$var reg 16 + data_in [15:0] $end
$var reg 1 , start $end
$scope module CON $end
$var wire 1 * clk $end
$var wire 1 , start $end
$var wire 1 $ lt $end
$var wire 1 ' gt $end
$var wire 1 ( eq $end
$var parameter 3 - s0 $end
$var parameter 3 . s1 $end
$var parameter 3 / s2 $end
$var parameter 3 0 s3 $end
$var parameter 3 1 s4 $end
$var parameter 3 2 s5 $end
$var reg 1 ) done $end
$var reg 1 & ldA $end
$var reg 1 % ldB $end
$var reg 1 # sel1 $end
$var reg 1 " sel2 $end
$var reg 1 ! sel_load $end
$var reg 3 3 state [2:0] $end
$upscope $end
$scope module DP $end
$var wire 1 * clk $end
$var wire 16 4 data_in [15:0] $end
$var wire 1 & ldA $end
$var wire 1 % ldB $end
$var wire 1 # sel1 $end
$var wire 1 " sel2 $end
$var wire 1 ! sel_load $end
$var wire 16 5 y [15:0] $end
$var wire 16 6 x [15:0] $end
$var wire 16 7 subout [15:0] $end
$var wire 1 $ lt $end
$var wire 1 ' gt $end
$var wire 1 ( eq $end
$var wire 16 8 Bus [15:0] $end
$var wire 16 9 Bout [15:0] $end
$var wire 16 : Aout [15:0] $end
$scope module A $end
$var wire 1 * clk $end
$var wire 1 & ld $end
$var wire 16 ; din [15:0] $end
$var reg 16 < dout [15:0] $end
$upscope $end
$scope module B $end
$var wire 1 * clk $end
$var wire 1 % ld $end
$var wire 16 = din [15:0] $end
$var reg 16 > dout [15:0] $end
$upscope $end
$scope module COMP $end
$var wire 16 ? in0 [15:0] $end
$var wire 16 @ in1 [15:0] $end
$var wire 1 $ lt $end
$var wire 1 ' gt $end
$var wire 1 ( eq $end
$upscope $end
$scope module MUX1 $end
$var wire 16 A in0 [15:0] $end
$var wire 16 B in1 [15:0] $end
$var wire 1 # sel $end
$var wire 16 C out [15:0] $end
$upscope $end
$scope module MUX2 $end
$var wire 16 D in0 [15:0] $end
$var wire 16 E in1 [15:0] $end
$var wire 1 " sel $end
$var wire 16 F out [15:0] $end
$upscope $end
$scope module MUX_load $end
$var wire 16 G in1 [15:0] $end
$var wire 1 ! sel $end
$var wire 16 H out [15:0] $end
$var wire 16 I in0 [15:0] $end
$upscope $end
$scope module SUBTRACTOR $end
$var wire 16 J data1 [15:0] $end
$var wire 16 K data2 [15:0] $end
$var reg 16 L out [15:0] $end
$upscope $end
$upscope $end
$upscope $end
$enddefinitions $end
$comment Show the parameter values. $end
$dumpall
b101 2
b100 1
b11 0
b10 /
b1 .
b0 -
$end
#0
$dumpvars
bx L
bx K
bx J
bx I
bx H
bx G
bx F
bx E
bx D
bx C
bx B
bx A
bx @
bx ?
bx >
bx =
bx <
bx ;
bx :
bx 9
bx 8
bx 7
bx 6
bx 5
bx 4
bx 3
x,
bx +
0*
x)
x(
x'
x&
x%
x$
x#
x"
x!
$end
#3
1,
#5
0)
0%
1&
1!
b0 3
1*
#10
0*
#12
b10001111 8
b10001111 ;
b10001111 =
b10001111 H
b10001111 +
b10001111 4
b10001111 G
#15
1%
0&
b1 3
b10001111 :
b10001111 <
b10001111 ?
b10001111 B
b10001111 E
1*
#20
0*
#22
b1001110 8
b1001110 ;
b1001110 =
b1001110 H
b1001110 +
b1001110 4
b1001110 G
#25
b1000001 7
b1000001 I
b1000001 L
b1000001 8
b1000001 ;
b1000001 =
b1000001 H
b10001111 6
b10001111 C
b10001111 J
b1001110 5
b1001110 F
b1001110 K
1&
0%
0!
0"
1#
0$
1'
0(
b1001110 9
b1001110 >
b1001110 @
b1001110 A
b1001110 D
b10 3
1*
#30
0*
#35
b1101 8
b1101 ;
b1101 =
b1101 H
b1101 7
b1101 I
b1101 L
b1000001 5
b1000001 F
b1000001 K
1%
0&
1"
0#
b1001110 6
b1001110 C
b1001110 J
b100 3
1$
0'
b1000001 :
b1000001 <
b1000001 ?
b1000001 B
b1000001 E
1*
#40
0*
#45
b110100 8
b110100 ;
b110100 =
b110100 H
b110100 7
b110100 I
b110100 L
b1101 5
b1101 F
b1101 K
b1000001 6
b1000001 C
b1000001 J
1&
0%
0"
1#
0$
1'
b1101 9
b1101 >
b1101 @
b1101 A
b1101 D
b11 3
1*
#50
0*
#55
b100111 8
b100111 ;
b100111 =
b100111 H
b100111 7
b100111 I
b100111 L
b110100 6
b110100 C
b110100 J
b100 3
b110100 :
b110100 <
b110100 ?
b110100 B
b110100 E
1*
#60
0*
#65
b11010 8
b11010 ;
b11010 =
b11010 H
b11010 7
b11010 I
b11010 L
b100111 6
b100111 C
b100111 J
b100111 :
b100111 <
b100111 ?
b100111 B
b100111 E
1*
#70
0*
#75
b1101 8
b1101 ;
b1101 =
b1101 H
b1101 7
b1101 I
b1101 L
b11010 6
b11010 C
b11010 J
b11010 :
b11010 <
b11010 ?
b11010 B
b11010 E
1*
#80
0*
#85
b0 8
b0 ;
b0 =
b0 H
b0 7
b0 I
b0 L
b1101 6
b1101 C
b1101 J
0'
1(
b1101 :
b1101 <
b1101 ?
b1101 B
b1101 E
1*
#90
0*
#95
b1111111111110011 8
b1111111111110011 ;
b1111111111110011 =
b1111111111110011 H
b1111111111110011 7
b1111111111110011 I
b1111111111110011 L
0&
1)
b0 6
b0 C
b0 J
b101 3
1$
0(
b0 :
b0 <
b0 ?
b0 B
b0 E
1*
