mux/mux_4x1.v
module mux_4x1(in,sel,out);
input [3:0]in;
input [1:0]sel;
output out;
assign out=in[sel];
endmodule

mux/mux16x1.v
module mux16x1(IN,SEL,OUT);
input [15:0]IN;
input [3:0]SEL;
output OUT;

wire [3:0]t;

mux_4x1 m1(.in(IN[3:0]),.sel(SEL[1:0]),.out(t[0]));
mux_4x1 m2(.in(IN[7:4]),.sel(SEL[1:0]),.out(t[1]));
mux_4x1 m3(.in(IN[11:8]),.sel(SEL[1:0]),.out(t[2]));
mux_4x1 m4(.in(IN[15:12]),.sel(SEL[1:0]),.out(t[3]));
mux_4x1 m5(.in(t),.sel(SEL[3:2]),.out(OUT));

endmodule

mux/muxtb.v
module muxtb;

// Declare inputs as reg and output as wire
reg [15:0] IN;
reg [3:0] SEL;
wire OUT;

// Instantiate the mux16x1 module
mux16x1 m(.IN(IN), .SEL(SEL), .OUT(OUT));

initial 
begin
  // Create a VCD file for waveform analysis
  $dumpfile("sim_res.vcd"); 
  $dumpvars(0, muxtb); 

  // End simulation after 1000 time units
  #1000 $finish;
end

initial 
begin
  // Apply different inputs and selection signals
  #50 IN = 16'b0000_0000_0000_0001; SEL = 4'b0001;
  #50 IN = 16'b0000_0000_0000_0011; SEL = 4'b0010;
  #50 IN = 16'b0000_0000_0000_0101; SEL = 4'b0011;
  #50 IN = 16'b0000_0000_0000_1001; SEL = 4'b0100;
  #50 IN = 16'b0000_0000_0001_0001; SEL = 4'b0101;
  #50 IN = 16'b0000_0000_0010_0001; SEL = 4'b0110;
  #50 IN = 16'b0000_0000_0010_0001; SEL = 4'b0111;
  #50 IN = 16'b0000_0000_0100_0001; SEL = 4'b1000;
  #50 IN = 16'b0000_0000_1000_0001; SEL = 4'b1001;
end

endmodule

mux/sim_res.vcd
$date
	Fri Sep 13 11:12:27 2024
$end
$version
	Icarus Verilog
$end
$timescale
	1s
$end
$scope module muxtb $end
$var wire 1 ! OUT $end
$var reg 16 " IN [15:0] $end
$var reg 4 # SEL [3:0] $end
$scope module m $end
$var wire 16 $ IN [15:0] $end
$var wire 4 % SEL [3:0] $end
$var wire 4 & t [3:0] $end
$var wire 1 ! OUT $end
$scope module m1 $end
$var wire 4 ' in [3:0] $end
$var wire 2 ( sel [1:0] $end
$var wire 1 ) out $end
$upscope $end
$scope module m2 $end
$var wire 4 * in [3:0] $end
$var wire 2 + sel [1:0] $end
$var wire 1 , out $end
$upscope $end
$scope module m3 $end
$var wire 4 - in [3:0] $end
$var wire 2 . sel [1:0] $end
$var wire 1 / out $end
$upscope $end
$scope module m4 $end
$var wire 4 0 in [3:0] $end
$var wire 2 1 sel [1:0] $end
$var wire 1 2 out $end
$upscope $end
$scope module m5 $end
$var wire 4 3 in [3:0] $end
$var wire 2 4 sel [1:0] $end
$var wire 1 ! out $end
$upscope $end
$upscope $end
$upscope $end
$enddefinitions $end
$comment Show the parameter values. $end
$dumpall
$end
#0
$dumpvars
bx 4
bx 3
x2
bx 1
bx 0
x/
bx .
bx -
x,
bx +
bx *
x)
bx (
bx '
bx &
bx %
bx $
bx #
bx "
x!
$end
#50
0!
b0 &
b0 3
0)
b1 (
0,
b1 +
0/
b1 .
02
b1 1
b0 4
b1 '
b0 *
b0 -
b0 0
b1 #
b1 %
b1 "
b1 $
#100
b10 (
b10 +
b10 .
b10 1
0)
b11 '
b10 #
b10 %
b11 "
b11 $
#150
b11 (
b11 +
b11 .
b11 1
0)
b101 '
b11 #
b11 %
b101 "
b101 $
#200
b1 &
b1 3
b0 (
b0 +
b0 .
b0 1
b1 4
1)
b1001 '
b100 #
b100 %
b1001 "
b1001 $
#250
b0 &
b0 3
0)
b1 (
b1 +
b1 .
b1 1
b1 '
0,
b1 *
b101 #
b101 %
b10001 "
b10001 $
#300
b10 (
b10 +
b10 .
b10 1
0,
b10 *
b110 #
b110 %
b100001 "
b100001 $
#350
b11 (
b11 +
b11 .
b11 1
b111 #
b111 %
#400
b1 &
b1 3
1)
b0 (
b0 +
b0 .
b0 1
b10 4
b100 *
b1000 #
b1000 %
b1000001 "
b1000001 $
#450
b0 &
b0 3
0)
b1 (
b1 +
b1 .
b1 1
b1000 *
b1001 #
b1001 %
b10000001 "
b10000001 $
