RESTORING_DIVIDER/controller.v
module controller(
input start,flag,clk,
output reg ldA,sel3,ldB,clrQ,incQ,
output reg done);
parameter s0=2'b00, s1=2'b01, s2=2'b10, s3=2'b11;
reg [2:0]state;

always @(posedge clk) begin
	case(state)
		s0: if(start) state<=s1;
		s1: state<=s2;
		s2: if(flag) state<=s3;
		    else state<=s2;
	        s3:state<=s3;
	        default:state<=s0; 
	 endcase
                      end

always @(state)begin
	case(state)
		s0: begin ldA=1; sel3=0; ldB=0; clrQ=1; incQ=0; done=0;end
		s1: begin ldA=0; sel3=0; ldB=1; clrQ=0; end
		s2: begin ldA=1;ldB=0; incQ=1; sel3=1; end
		s3: begin incQ=0; done=1; end
 		default: begin ldA=1; sel3=0; ldB=0; clrQ=1; incQ=0; end
	endcase
                end
endmodule

RESTORING_DIVIDER/MUX.v
module MUX(out,sel,in0,in1);
input [7:0]in0,in1;
input sel;
output [7:0]out;

assign out=sel?in1:in0;
endmodule

RESTORING_DIVIDER/SUB.v
module SUB(
    output reg signed [7:0] result, // Make result signed
    output reg flag,
    input signed [7:0] d1, d2
);

always @(*) begin
    result = d1 - d2;
    if (result < 0)
        flag = 1'b1;
    else
        flag = 1'b0;
end

endmodule

RESTORING_DIVIDER/shiftreg.v
module shiftreg(
input clr,inc,clk,
output reg [7:0]q
);

always @(posedge clk)begin
	if(clr) q<=0;
	else if(inc) q=q+1;
end
endmodule

RESTORING_DIVIDER/PIPO.v
module PIPO(
input [7:0]din,
input ld,
input clk,
output reg [7:0]dout);


always @(posedge clk)begin
	if(ld) dout<=din;

end
endmodule

RESTORING_DIVIDER/divider.v
module divider(
    input signed [7:0] data_in,
    output [7:0] Q,
    output done,
    input start, clk
);

    // Declaring internal signals
    wire signed [7:0] W, X, Z;
    wire FLAG;
    wire signed [7:0] Bus;
    wire ldA, ldB, clrQ, incQ;
    wire sel3; // Added missing 'sel3' wire

    // Instantiating PIPO registers
    PIPO A1(Bus, ldA, clk, W); // W stores the result from A1
    PIPO B1(Bus, ldB, clk, X); // X stores the result from B1

    // Instantiating shift register
    shiftreg QQ(clrQ, incQ, clk, Q);

    // Instantiating subtractor
    SUB SSB(Z, FLAG, W, X); // Z is the result, FLAG signals the condition

    // Instantiating multiplexer
    MUX m3(Bus, sel3, data_in, Z); // MUX chooses between data_in and Z

    // Instantiating controller
    controller cot(start, FLAG, clk, ldA, sel3, ldB, clrQ, incQ, done);

endmodule

RESTORING_DIVIDER/tb.v
module tb;

    reg [7:0] data_in;
    reg start;
    wire done;
    reg clk;
    wire [7:0] Q;

    // Named instantiation of the divider module
    divider check(
        .data_in(data_in),
        .Q(Q),
        .done(done),
        .start(start),
        .clk(clk)
    );

    // Clock generation
    initial clk = 1'b0;
    always #5 clk = ~clk;

    // Test sequence
    initial begin
        $dumpfile("res.vcd"); 
        $dumpvars(0, tb); // dumping all signals at level 0
        
        // Wait for 10 time units, then start the process
        #10 start = 1'b1; // Start signal to initiate the division
         // Lower the start signal after one clock cycle
        data_in = 8'd50; // Load first value (numerator)
        
        // Wait for some time, then provide the second value
        #10 data_in = 8'd2; // Load second value (denominator)

        // Wait for the division process to finish
        #1000 $finish;
    end

endmodule

RESTORING_DIVIDER/res.vcd
$date
	Mon Sep 30 14:46:44 2024
$end
$version
	Icarus Verilog
$end
$timescale
	1s
$end
$scope module tb $end
$var wire 1 ! done $end
$var wire 8 " Q [7:0] $end
$var reg 1 # clk $end
$var reg 8 $ data_in [7:0] $end
$var reg 1 % start $end
$scope module check $end
$var wire 1 # clk $end
$var wire 8 & data_in [7:0] $end
$var wire 1 % start $end
$var wire 1 ' sel3 $end
$var wire 1 ( ldB $end
$var wire 1 ) ldA $end
$var wire 1 * incQ $end
$var wire 1 ! done $end
$var wire 1 + clrQ $end
$var wire 8 , Z [7:0] $end
$var wire 8 - X [7:0] $end
$var wire 8 . W [7:0] $end
$var wire 8 / Q [7:0] $end
$var wire 1 0 FLAG $end
$var wire 8 1 Bus [7:0] $end
$scope module A1 $end
$var wire 1 # clk $end
$var wire 1 ) ld $end
$var wire 8 2 din [7:0] $end
$var reg 8 3 dout [7:0] $end
$upscope $end
$scope module B1 $end
$var wire 1 # clk $end
$var wire 1 ( ld $end
$var wire 8 4 din [7:0] $end
$var reg 8 5 dout [7:0] $end
$upscope $end
$scope module QQ $end
$var wire 1 # clk $end
$var wire 1 * inc $end
$var wire 1 + clr $end
$var reg 8 6 q [7:0] $end
$upscope $end
$scope module SSB $end
$var wire 8 7 d1 [7:0] $end
$var wire 8 8 d2 [7:0] $end
$var reg 1 0 flag $end
$var reg 8 9 result [7:0] $end
$upscope $end
$scope module cot $end
$var wire 1 # clk $end
$var wire 1 0 flag $end
$var wire 1 % start $end
$var parameter 2 : s0 $end
$var parameter 2 ; s1 $end
$var parameter 2 < s2 $end
$var parameter 2 = s3 $end
$var reg 1 + clrQ $end
$var reg 1 ! done $end
$var reg 1 * incQ $end
$var reg 1 ) ldA $end
$var reg 1 ( ldB $end
$var reg 1 ' sel3 $end
$var reg 3 > state [2:0] $end
$upscope $end
$scope module m3 $end
$var wire 8 ? in0 [7:0] $end
$var wire 8 @ in1 [7:0] $end
$var wire 1 ' sel $end
$var wire 8 A out [7:0] $end
$upscope $end
$upscope $end
$upscope $end
$enddefinitions $end
$comment Show the parameter values. $end
$dumpall
b11 =
b10 <
b1 ;
b0 :
$end
#0
$dumpvars
bx A
bx @
bx ?
bx >
bx 9
bx 8
bx 7
bx 6
bx 5
bx 4
bx 3
bx 2
bx 1
x0
bx /
bx .
bx -
bx ,
x+
x*
x)
x(
x'
bx &
x%
bx $
0#
bx "
x!
$end
#5
0!
0*
1+
0(
0'
1)
b0 >
1#
#10
b110010 1
b110010 2
b110010 4
b110010 A
0#
b110010 $
b110010 &
b110010 ?
1%
#15
0+
1(
0)
00
b1 >
b0 "
b0 /
b0 6
b110010 .
b110010 3
b110010 7
1#
#20
b10 1
b10 2
b10 4
b10 A
0#
b10 $
b10 &
b10 ?
#25
b110000 1
b110000 2
b110000 4
b110000 A
b110000 ,
b110000 9
b110000 @
1'
1*
0(
1)
b10 -
b10 5
b10 8
b10 >
1#
#30
0#
#35
b101110 1
b101110 2
b101110 4
b101110 A
b101110 ,
b101110 9
b101110 @
b110000 .
b110000 3
b110000 7
b1 "
b1 /
b1 6
1#
#40
0#
#45
b101100 1
b101100 2
b101100 4
b101100 A
b101100 ,
b101100 9
b101100 @
b101110 .
b101110 3
b101110 7
b10 "
b10 /
b10 6
1#
#50
0#
#55
b101010 1
b101010 2
b101010 4
b101010 A
b101010 ,
b101010 9
b101010 @
b101100 .
b101100 3
b101100 7
b11 "
b11 /
b11 6
1#
#60
0#
#65
b101000 1
b101000 2
b101000 4
b101000 A
b101000 ,
b101000 9
b101000 @
b101010 .
b101010 3
b101010 7
b100 "
b100 /
b100 6
1#
#70
0#
#75
b100110 1
b100110 2
b100110 4
b100110 A
b100110 ,
b100110 9
b100110 @
b101000 .
b101000 3
b101000 7
b101 "
b101 /
b101 6
1#
#80
0#
#85
b100100 1
b100100 2
b100100 4
b100100 A
b100100 ,
b100100 9
b100100 @
b100110 .
b100110 3
b100110 7
b110 "
b110 /
b110 6
1#
#90
0#
#95
b100010 1
b100010 2
b100010 4
b100010 A
b100010 ,
b100010 9
b100010 @
b100100 .
b100100 3
b100100 7
b111 "
b111 /
b111 6
1#
#100
0#
#105
b100000 1
b100000 2
b100000 4
b100000 A
b100000 ,
b100000 9
b100000 @
b100010 .
b100010 3
b100010 7
b1000 "
b1000 /
b1000 6
1#
#110
0#
#115
b11110 1
b11110 2
b11110 4
b11110 A
b11110 ,
b11110 9
b11110 @
b100000 .
b100000 3
b100000 7
b1001 "
b1001 /
b1001 6
1#
#120
0#
#125
b11100 1
b11100 2
b11100 4
b11100 A
b11100 ,
b11100 9
b11100 @
b11110 .
b11110 3
b11110 7
b1010 "
b1010 /
b1010 6
1#
#130
0#
#135
b11010 1
b11010 2
b11010 4
b11010 A
b11010 ,
b11010 9
b11010 @
b11100 .
b11100 3
b11100 7
b1011 "
b1011 /
b1011 6
1#
#140
0#
#145
b11000 1
b11000 2
b11000 4
b11000 A
b11000 ,
b11000 9
b11000 @
b11010 .
b11010 3
b11010 7
b1100 "
b1100 /
b1100 6
1#
#150
0#
#155
b10110 1
b10110 2
b10110 4
b10110 A
b10110 ,
b10110 9
b10110 @
b11000 .
b11000 3
b11000 7
b1101 "
b1101 /
b1101 6
1#
#160
0#
#165
b10100 1
b10100 2
b10100 4
b10100 A
b10100 ,
b10100 9
b10100 @
b10110 .
b10110 3
b10110 7
b1110 "
b1110 /
b1110 6
1#
#170
0#
#175
b10010 1
b10010 2
b10010 4
b10010 A
b10010 ,
b10010 9
b10010 @
b10100 .
b10100 3
b10100 7
b1111 "
b1111 /
b1111 6
1#
#180
0#
#185
b10000 1
b10000 2
b10000 4
b10000 A
b10000 ,
b10000 9
b10000 @
b10010 .
b10010 3
b10010 7
b10000 "
b10000 /
b10000 6
1#
#190
0#
#195
b1110 1
b1110 2
b1110 4
b1110 A
b1110 ,
b1110 9
b1110 @
b10000 .
b10000 3
b10000 7
b10001 "
b10001 /
b10001 6
1#
#200
0#
#205
b1100 1
b1100 2
b1100 4
b1100 A
b1100 ,
b1100 9
b1100 @
b1110 .
b1110 3
b1110 7
b10010 "
b10010 /
b10010 6
1#
#210
0#
#215
b1010 1
b1010 2
b1010 4
b1010 A
b1010 ,
b1010 9
b1010 @
b1100 .
b1100 3
b1100 7
b10011 "
b10011 /
b10011 6
1#
#220
0#
#225
b1000 1
b1000 2
b1000 4
b1000 A
b1000 ,
b1000 9
b1000 @
b1010 .
b1010 3
b1010 7
b10100 "
b10100 /
b10100 6
1#
#230
0#
#235
b110 1
b110 2
b110 4
b110 A
b110 ,
b110 9
b110 @
b1000 .
b1000 3
b1000 7
b10101 "
b10101 /
b10101 6
1#
#240
0#
#245
b100 1
b100 2
b100 4
b100 A
b100 ,
b100 9
b100 @
b110 .
b110 3
b110 7
b10110 "
b10110 /
b10110 6
1#
#250
0#
#255
b10 1
b10 2
b10 4
b10 A
b10 ,
b10 9
b10 @
b100 .
b100 3
b100 7
b10111 "
b10111 /
b10111 6
1#
#260
0#
#265
b0 1
b0 2
b0 4
b0 A
b0 ,
b0 9
b0 @
b10 .
b10 3
b10 7
b11000 "
b11000 /
b11000 6
1#
#270
0#
#275
b11111110 1
b11111110 2
b11111110 4
b11111110 A
10
b11111110 ,
b11111110 9
b11111110 @
b0 .
b0 3
b0 7
b11001 "
b11001 /
b11001 6
1#
#280
0#
#285
b11111100 1
b11111100 2
b11111100 4
b11111100 A
b11111100 ,
b11111100 9
b11111100 @
1!
0*
b11111110 .
b11111110 3
b11111110 7
b11 >
b11010 "
b11010 /
b11010 6
1#
#290
0#
#295
b11111010 1
b11111010 2
b11111010 4
b11111010 A
b11111010 ,
b11111010 9
b11111010 @
b11111100 .
b11111100 3
b11111100 7
1#
#300
0#
#305
b11111000 1
b11111000 2
b11111000 4
b11111000 A
b11111000 ,
b11111000 9
b11111000 @
b11111010 .
b11111010 3
b11111010 7
1#
#310
0#
#315
b11110110 1
b11110110 2
b11110110 4
b11110110 A
b11110110 ,
b11110110 9
b11110110 @
b11111000 .
b11111000 3
b11111000 7
1#
#320
0#
#325
b11110100 1
b11110100 2
b11110100 4
b11110100 A
b11110100 ,
b11110100 9
b11110100 @
b11110110 .
b11110110 3
b11110110 7
1#
#330
0#
#335
b11110010 1
b11110010 2
b11110010 4
b11110010 A
b11110010 ,
b11110010 9
b11110010 @
b11110100 .
b11110100 3
b11110100 7
1#
#340
0#
#345
b11110000 1
b11110000 2
b11110000 4
b11110000 A
b11110000 ,
b11110000 9
b11110000 @
b11110010 .
b11110010 3
b11110010 7
1#
#350
0#
#355
b11101110 1
b11101110 2
b11101110 4
b11101110 A
b11101110 ,
b11101110 9
b11101110 @
b11110000 .
b11110000 3
b11110000 7
1#
#360
0#
#365
b11101100 1
b11101100 2
b11101100 4
b11101100 A
b11101100 ,
b11101100 9
b11101100 @
b11101110 .
b11101110 3
b11101110 7
1#
#370
0#
#375
b11101010 1
b11101010 2
b11101010 4
b11101010 A
b11101010 ,
b11101010 9
b11101010 @
b11101100 .
b11101100 3
b11101100 7
1#
#380
0#
#385
b11101000 1
b11101000 2
b11101000 4
b11101000 A
b11101000 ,
b11101000 9
b11101000 @
b11101010 .
b11101010 3
b11101010 7
1#
#390
0#
#395
b11100110 1
b11100110 2
b11100110 4
b11100110 A
b11100110 ,
b11100110 9
b11100110 @
b11101000 .
b11101000 3
b11101000 7
1#
#400
0#
#405
b11100100 1
b11100100 2
b11100100 4
b11100100 A
b11100100 ,
b11100100 9
b11100100 @
b11100110 .
b11100110 3
b11100110 7
1#
#410
0#
#415
b11100010 1
b11100010 2
b11100010 4
b11100010 A
b11100010 ,
b11100010 9
b11100010 @
b11100100 .
b11100100 3
b11100100 7
1#
#420
0#
#425
b11100000 1
b11100000 2
b11100000 4
b11100000 A
b11100000 ,
b11100000 9
b11100000 @
b11100010 .
b11100010 3
b11100010 7
1#
#430
0#
#435
b11011110 1
b11011110 2
b11011110 4
b11011110 A
b11011110 ,
b11011110 9
b11011110 @
b11100000 .
b11100000 3
b11100000 7
1#
#440
0#
#445
b11011100 1
b11011100 2
b11011100 4
b11011100 A
b11011100 ,
b11011100 9
b11011100 @
b11011110 .
b11011110 3
b11011110 7
1#
#450
0#
#455
b11011010 1
b11011010 2
b11011010 4
b11011010 A
b11011010 ,
b11011010 9
b11011010 @
b11011100 .
b11011100 3
b11011100 7
1#
#460
0#
#465
b11011000 1
b11011000 2
b11011000 4
b11011000 A
b11011000 ,
b11011000 9
b11011000 @
b11011010 .
b11011010 3
b11011010 7
1#
#470
0#
#475
b11010110 1
b11010110 2
b11010110 4
b11010110 A
b11010110 ,
b11010110 9
b11010110 @
b11011000 .
b11011000 3
b11011000 7
1#
#480
0#
#485
b11010100 1
b11010100 2
b11010100 4
b11010100 A
b11010100 ,
b11010100 9
b11010100 @
b11010110 .
b11010110 3
b11010110 7
1#
#490
0#
#495
b11010010 1
b11010010 2
b11010010 4
b11010010 A
b11010010 ,
b11010010 9
b11010010 @
b11010100 .
b11010100 3
b11010100 7
1#
#500
0#
#505
b11010000 1
b11010000 2
b11010000 4
b11010000 A
b11010000 ,
b11010000 9
b11010000 @
b11010010 .
b11010010 3
b11010010 7
1#
#510
0#
#515
b11001110 1
b11001110 2
b11001110 4
b11001110 A
b11001110 ,
b11001110 9
b11001110 @
b11010000 .
b11010000 3
b11010000 7
1#
#520
0#
#525
b11001100 1
b11001100 2
b11001100 4
b11001100 A
b11001100 ,
b11001100 9
b11001100 @
b11001110 .
b11001110 3
b11001110 7
1#
#530
0#
#535
b11001010 1
b11001010 2
b11001010 4
b11001010 A
b11001010 ,
b11001010 9
b11001010 @
b11001100 .
b11001100 3
b11001100 7
1#
#540
0#
#545
b11001000 1
b11001000 2
b11001000 4
b11001000 A
b11001000 ,
b11001000 9
b11001000 @
b11001010 .
b11001010 3
b11001010 7
1#
#550
0#
#555
b11000110 1
b11000110 2
b11000110 4
b11000110 A
b11000110 ,
b11000110 9
b11000110 @
b11001000 .
b11001000 3
b11001000 7
1#
#560
0#
#565
b11000100 1
b11000100 2
b11000100 4
b11000100 A
b11000100 ,
b11000100 9
b11000100 @
b11000110 .
b11000110 3
b11000110 7
1#
#570
0#
#575
b11000010 1
b11000010 2
b11000010 4
b11000010 A
b11000010 ,
b11000010 9
b11000010 @
b11000100 .
b11000100 3
b11000100 7
1#
#580
0#
#585
b11000000 1
b11000000 2
b11000000 4
b11000000 A
b11000000 ,
b11000000 9
b11000000 @
b11000010 .
b11000010 3
b11000010 7
1#
#590
0#
#595
b10111110 1
b10111110 2
b10111110 4
b10111110 A
b10111110 ,
b10111110 9
b10111110 @
b11000000 .
b11000000 3
b11000000 7
1#
#600
0#
#605
b10111100 1
b10111100 2
b10111100 4
b10111100 A
b10111100 ,
b10111100 9
b10111100 @
b10111110 .
b10111110 3
b10111110 7
1#
#610
0#
#615
b10111010 1
b10111010 2
b10111010 4
b10111010 A
b10111010 ,
b10111010 9
b10111010 @
b10111100 .
b10111100 3
b10111100 7
1#
#620
0#
#625
b10111000 1
b10111000 2
b10111000 4
b10111000 A
b10111000 ,
b10111000 9
b10111000 @
b10111010 .
b10111010 3
b10111010 7
1#
#630
0#
#635
b10110110 1
b10110110 2
b10110110 4
b10110110 A
b10110110 ,
b10110110 9
b10110110 @
b10111000 .
b10111000 3
b10111000 7
1#
#640
0#
#645
b10110100 1
b10110100 2
b10110100 4
b10110100 A
b10110100 ,
b10110100 9
b10110100 @
b10110110 .
b10110110 3
b10110110 7
1#
#650
0#
#655
b10110010 1
b10110010 2
b10110010 4
b10110010 A
b10110010 ,
b10110010 9
b10110010 @
b10110100 .
b10110100 3
b10110100 7
1#
#660
0#
#665
b10110000 1
b10110000 2
b10110000 4
b10110000 A
b10110000 ,
b10110000 9
b10110000 @
b10110010 .
b10110010 3
b10110010 7
1#
#670
0#
#675
b10101110 1
b10101110 2
b10101110 4
b10101110 A
b10101110 ,
b10101110 9
b10101110 @
b10110000 .
b10110000 3
b10110000 7
1#
#680
0#
#685
b10101100 1
b10101100 2
b10101100 4
b10101100 A
b10101100 ,
b10101100 9
b10101100 @
b10101110 .
b10101110 3
b10101110 7
1#
#690
0#
#695
b10101010 1
b10101010 2
b10101010 4
b10101010 A
b10101010 ,
b10101010 9
b10101010 @
b10101100 .
b10101100 3
b10101100 7
1#
#700
0#
#705
b10101000 1
b10101000 2
b10101000 4
b10101000 A
b10101000 ,
b10101000 9
b10101000 @
b10101010 .
b10101010 3
b10101010 7
1#
#710
0#
#715
b10100110 1
b10100110 2
b10100110 4
b10100110 A
b10100110 ,
b10100110 9
b10100110 @
b10101000 .
b10101000 3
b10101000 7
1#
#720
0#
#725
b10100100 1
b10100100 2
b10100100 4
b10100100 A
b10100100 ,
b10100100 9
b10100100 @
b10100110 .
b10100110 3
b10100110 7
1#
#730
0#
#735
b10100010 1
b10100010 2
b10100010 4
b10100010 A
b10100010 ,
b10100010 9
b10100010 @
b10100100 .
b10100100 3
b10100100 7
1#
#740
0#
#745
b10100000 1
b10100000 2
b10100000 4
b10100000 A
b10100000 ,
b10100000 9
b10100000 @
b10100010 .
b10100010 3
b10100010 7
1#
#750
0#
#755
b10011110 1
b10011110 2
b10011110 4
b10011110 A
b10011110 ,
b10011110 9
b10011110 @
b10100000 .
b10100000 3
b10100000 7
1#
#760
0#
#765
b10011100 1
b10011100 2
b10011100 4
b10011100 A
b10011100 ,
b10011100 9
b10011100 @
b10011110 .
b10011110 3
b10011110 7
1#
#770
0#
#775
b10011010 1
b10011010 2
b10011010 4
b10011010 A
b10011010 ,
b10011010 9
b10011010 @
b10011100 .
b10011100 3
b10011100 7
1#
#780
0#
#785
b10011000 1
b10011000 2
b10011000 4
b10011000 A
b10011000 ,
b10011000 9
b10011000 @
b10011010 .
b10011010 3
b10011010 7
1#
#790
0#
#795
b10010110 1
b10010110 2
b10010110 4
b10010110 A
b10010110 ,
b10010110 9
b10010110 @
b10011000 .
b10011000 3
b10011000 7
1#
#800
0#
#805
b10010100 1
b10010100 2
b10010100 4
b10010100 A
b10010100 ,
b10010100 9
b10010100 @
b10010110 .
b10010110 3
b10010110 7
1#
#810
0#
#815
b10010010 1
b10010010 2
b10010010 4
b10010010 A
b10010010 ,
b10010010 9
b10010010 @
b10010100 .
b10010100 3
b10010100 7
1#
#820
0#
#825
b10010000 1
b10010000 2
b10010000 4
b10010000 A
b10010000 ,
b10010000 9
b10010000 @
b10010010 .
b10010010 3
b10010010 7
1#
#830
0#
#835
b10001110 1
b10001110 2
b10001110 4
b10001110 A
b10001110 ,
b10001110 9
b10001110 @
b10010000 .
b10010000 3
b10010000 7
1#
#840
0#
#845
b10001100 1
b10001100 2
b10001100 4
b10001100 A
b10001100 ,
b10001100 9
b10001100 @
b10001110 .
b10001110 3
b10001110 7
1#
#850
0#
#855
b10001010 1
b10001010 2
b10001010 4
b10001010 A
b10001010 ,
b10001010 9
b10001010 @
b10001100 .
b10001100 3
b10001100 7
1#
#860
0#
#865
b10001000 1
b10001000 2
b10001000 4
b10001000 A
b10001000 ,
b10001000 9
b10001000 @
b10001010 .
b10001010 3
b10001010 7
1#
#870
0#
#875
b10000110 1
b10000110 2
b10000110 4
b10000110 A
b10000110 ,
b10000110 9
b10000110 @
b10001000 .
b10001000 3
b10001000 7
1#
#880
0#
#885
b10000100 1
b10000100 2
b10000100 4
b10000100 A
b10000100 ,
b10000100 9
b10000100 @
b10000110 .
b10000110 3
b10000110 7
1#
#890
0#
#895
b10000010 1
b10000010 2
b10000010 4
b10000010 A
b10000010 ,
b10000010 9
b10000010 @
b10000100 .
b10000100 3
b10000100 7
1#
#900
0#
#905
b10000000 1
b10000000 2
b10000000 4
b10000000 A
b10000000 ,
b10000000 9
b10000000 @
b10000010 .
b10000010 3
b10000010 7
1#
#910
0#
#915
b1111110 1
b1111110 2
b1111110 4
b1111110 A
00
b1111110 ,
b1111110 9
b1111110 @
b10000000 .
b10000000 3
b10000000 7
1#
#920
0#
#925
b1111100 1
b1111100 2
b1111100 4
b1111100 A
b1111100 ,
b1111100 9
b1111100 @
b1111110 .
b1111110 3
b1111110 7
1#
#930
0#
#935
b1111010 1
b1111010 2
b1111010 4
b1111010 A
b1111010 ,
b1111010 9
b1111010 @
b1111100 .
b1111100 3
b1111100 7
1#
#940
0#
#945
b1111000 1
b1111000 2
b1111000 4
b1111000 A
b1111000 ,
b1111000 9
b1111000 @
b1111010 .
b1111010 3
b1111010 7
1#
#950
0#
#955
b1110110 1
b1110110 2
b1110110 4
b1110110 A
b1110110 ,
b1110110 9
b1110110 @
b1111000 .
b1111000 3
b1111000 7
1#
#960
0#
#965
b1110100 1
b1110100 2
b1110100 4
b1110100 A
b1110100 ,
b1110100 9
b1110100 @
b1110110 .
b1110110 3
b1110110 7
1#
#970
0#
#975
b1110010 1
b1110010 2
b1110010 4
b1110010 A
b1110010 ,
b1110010 9
b1110010 @
b1110100 .
b1110100 3
b1110100 7
1#
#980
0#
#985
b1110000 1
b1110000 2
b1110000 4
b1110000 A
b1110000 ,
b1110000 9
b1110000 @
b1110010 .
b1110010 3
b1110010 7
1#
#990
0#
#995
b1101110 1
b1101110 2
b1101110 4
b1101110 A
b1101110 ,
b1101110 9
b1101110 @
b1110000 .
b1110000 3
b1110000 7
1#
#1000
0#
#1005
b1101100 1
b1101100 2
b1101100 4
b1101100 A
b1101100 ,
b1101100 9
b1101100 @
b1101110 .
b1101110 3
b1101110 7
1#
#1010
0#
#1015
b1101010 1
b1101010 2
b1101010 4
b1101010 A
b1101010 ,
b1101010 9
b1101010 @
b1101100 .
b1101100 3
b1101100 7
1#
