PWM/pwmsignal.v
module pwmsignal(
input clk,rst,
output reg dout);
reg [3:0]count;
reg [3:0]ton;
reg ncyc;
parameter TP=5;
always @(posedge clk)
begin
	if(rst)
	begin
		count<=0;
		ton<=1;
		ncyc<=0;
	end
	else
	begin
		if(count<=ton)
		begin
			count<=count+1;
			dout<=1'b1;
			ncyc<=1'b0;
		end
		else if(count<TP)
		begin
			count<=count+1;
			dout<=1'b0;
			ncyc<=1'b0;
		end
		else 
		begin
		count<=0;
		ncyc<=1'b1;
		end
	end
end

always @(posedge clk)
begin
	if(ncyc)
		if(ton<TP)
			ton<=ton+1;
		else
			ton<=0;
end
endmodule

PWM/tb.v
module tb;

  // Inputs
  reg clk;
  reg rst;

  // Outputs
  wire dout;

  // Instantiate the PWM signal module
  pwmsignal uut (
    .clk(clk), 
    .rst(rst), 
    .dout(dout)
  );

  // Clock generation (50% duty cycle, 10 time units period)
  initial begin
    clk = 0;
    forever #5 clk = ~clk;  // Toggle the clock every 5 time units
  end

  // Test procedure
  initial begin
    // Dump the waveform to a VCD file
    $dumpfile("res.vcd"); // Specify the name of the output VCD file
    $dumpvars; // Dump all variables in the current module
    

    
    // Initialize inputs
    rst = 1;

    // Hold reset active for 20 time units
    #20 rst = 0;

    // Run the test for some time (200 time units)
    #200;

    // Reset again to see the behavior after reset
    #20 rst = 1;
    #20 rst = 0;

    // Continue simulation for another 200 time units
    #1000;

    // End simulation
    $finish;
  end

endmodule

PWM/res.vcd
$date
	Sun Oct 20 16:54:06 2024
$end
$version
	Icarus Verilog
$end
$timescale
	1s
$end
$scope module tb $end
$var wire 1 ! dout $end
$var reg 1 " clk $end
$var reg 1 # rst $end
$scope module uut $end
$var wire 1 " clk $end
$var wire 1 # rst $end
$var parameter 32 $ TP $end
$var reg 4 % count [3:0] $end
$var reg 1 ! dout $end
$var reg 1 & ncyc $end
$var reg 4 ' ton [3:0] $end
$upscope $end
$upscope $end
$enddefinitions $end
$comment Show the parameter values. $end
$dumpall
b101 $
$end
#0
$dumpvars
bx '
x&
bx %
1#
0"
x!
$end
#5
0&
b1 '
b0 %
1"
#10
0"
#15
1"
#20
0"
0#
#25
1!
b1 %
1"
#30
0"
#35
b10 %
1"
#40
0"
#45
0!
b11 %
1"
#50
0"
#55
b100 %
1"
#60
0"
#65
b101 %
1"
#70
0"
#75
1&
b0 %
1"
#80
0"
#85
0&
1!
b1 %
b10 '
1"
#90
0"
#95
b10 %
1"
#100
0"
#105
b11 %
1"
#110
0"
#115
0!
b100 %
1"
#120
0"
#125
b101 %
1"
#130
0"
#135
1&
b0 %
1"
#140
0"
#145
0&
1!
b1 %
b11 '
1"
#150
0"
#155
b10 %
1"
#160
0"
#165
b11 %
1"
#170
0"
#175
b100 %
1"
#180
0"
#185
0!
b101 %
1"
#190
0"
#195
1&
b0 %
1"
#200
0"
#205
0&
1!
b1 %
b100 '
1"
#210
0"
#215
b10 %
1"
#220
0"
#225
b11 %
1"
#230
0"
#235
b100 %
1"
#240
0"
1#
#245
b1 '
b0 %
1"
#250
0"
#255
1"
#260
0"
0#
#265
b1 %
1"
#270
0"
#275
b10 %
1"
#280
0"
#285
0!
b11 %
1"
#290
0"
#295
b100 %
1"
#300
0"
#305
b101 %
1"
#310
0"
#315
1&
b0 %
1"
#320
0"
#325
0&
1!
b1 %
b10 '
1"
#330
0"
#335
b10 %
1"
#340
0"
#345
b11 %
1"
#350
0"
#355
0!
b100 %
1"
#360
0"
#365
b101 %
1"
#370
0"
#375
1&
b0 %
1"
#380
0"
#385
0&
1!
b1 %
b11 '
1"
#390
0"
#395
b10 %
1"
#400
0"
#405
b11 %
1"
#410
0"
#415
b100 %
1"
#420
0"
#425
0!
b101 %
1"
#430
0"
#435
1&
b0 %
1"
#440
0"
#445
0&
1!
b1 %
b100 '
1"
#450
0"
#455
b10 %
1"
#460
0"
#465
b11 %
1"
#470
0"
#475
b100 %
1"
#480
0"
#485
b101 %
1"
#490
0"
#495
1&
b0 %
1"
#500
0"
#505
0&
b1 %
b101 '
1"
#510
0"
#515
b10 %
1"
#520
0"
#525
b11 %
1"
#530
0"
#535
b100 %
1"
#540
0"
#545
b101 %
1"
#550
0"
#555
b110 %
1"
#560
0"
#565
1&
b0 %
1"
#570
0"
#575
b0 '
0&
b1 %
1"
#580
0"
#585
0!
b10 %
1"
#590
0"
#595
b11 %
1"
#600
0"
#605
b100 %
1"
#610
0"
#615
b101 %
1"
#620
0"
#625
1&
b0 %
1"
#630
0"
#635
b1 '
0&
1!
b1 %
1"
#640
0"
#645
b10 %
1"
#650
0"
#655
0!
b11 %
1"
#660
0"
#665
b100 %
1"
#670
0"
#675
b101 %
1"
#680
0"
#685
1&
b0 %
1"
#690
0"
#695
b10 '
0&
1!
b1 %
1"
#700
0"
#705
b10 %
1"
#710
0"
#715
b11 %
1"
#720
0"
#725
0!
b100 %
1"
#730
0"
#735
b101 %
1"
#740
0"
#745
1&
b0 %
1"
#750
0"
#755
b11 '
0&
1!
b1 %
1"
#760
0"
#765
b10 %
1"
#770
0"
#775
b11 %
1"
#780
0"
#785
b100 %
1"
#790
0"
#795
0!
b101 %
1"
#800
0"
#805
1&
b0 %
1"
#810
0"
#815
b100 '
0&
1!
b1 %
1"
#820
0"
#825
b10 %
1"
#830
0"
#835
b11 %
1"
#840
0"
#845
b100 %
1"
#850
0"
#855
b101 %
1"
#860
0"
#865
1&
b0 %
1"
#870
0"
#875
b101 '
0&
b1 %
1"
#880
0"
#885
b10 %
1"
#890
0"
#895
b11 %
1"
#900
0"
#905
b100 %
1"
#910
0"
#915
b101 %
1"
#920
0"
#925
b110 %
1"
#930
0"
#935
1&
b0 %
1"
#940
0"
#945
0&
b1 %
b0 '
1"
#950
0"
#955
0!
b10 %
1"
#960
0"
#965
b11 %
1"
#970
0"
#975
b100 %
1"
#980
0"
#985
b101 %
1"
#990
0"
#995
1&
b0 %
1"
#1000
0"
#1005
0&
1!
b1 %
b1 '
1"
#1010
0"
#1015
b10 %
1"
#1020
0"
#1025
0!
b11 %
1"
#1030
0"
#1035
b100 %
1"
#1040
0"
#1045
b101 %
1"
#1050
0"
#1055
1&
b0 %
1"
#1060
0"
#1065
0&
1!
b1 %
b10 '
1"
#1070
0"
#1075
b10 %
1"
#1080
0"
#1085
b11 %
1"
#1090
0"
#1095
0!
b100 %
1"
#1100
0"
#1105
b101 %
1"
#1110
0"
#1115
1&
b0 %
1"
#1120
0"
#1125
0&
1!
b1 %
b11 '
1"
#1130
0"
#1135
b10 %
1"
#1140
0"
#1145
b11 %
1"
#1150
0"
#1155
b100 %
1"
#1160
0"
#1165
0!
b101 %
1"
#1170
0"
#1175
1&
b0 %
1"
#1180
0"
#1185
0&
1!
b1 %
b100 '
1"
#1190
0"
#1195
b10 %
1"
#1200
0"
#1205
b11 %
1"
#1210
0"
#1215
b100 %
1"
#1220
0"
#1225
b101 %
1"
#1230
0"
#1235
1&
b0 %
1"
#1240
0"
#1245
0&
b1 %
b101 '
1"
#1250
0"
#1255
b10 %
1"
